gke_logging/__init__.py
gke_logging/asgi.py
gke_logging/context.py
gke_logging/py.typed
gke_logging/pylogging.py
gke_logging/types.py
gke_logging-0.1.0.dist-info/LICENSE
gke_logging-0.1.0.dist-info/METADATA
gke_logging-0.1.0.dist-info/WHEEL
gke_logging-0.1.0.dist-info/RECORD
