Metadata-Version: 2.1
Name: gke-logging
Version: 0.1.0
Summary: Utilities for interacting with logging facilities in GKE workloads
License: MIT
Author: Station A
Author-email: oss@stationa.com
Requires-Python: >=3.8,<4.0
Classifier: License :: OSI Approved :: MIT License
Classifier: Programming Language :: Python :: 3
Classifier: Programming Language :: Python :: 3.8
Classifier: Programming Language :: Python :: 3.9
Classifier: Programming Language :: Python :: 3.10
Classifier: Programming Language :: Python :: 3.11
Classifier: Programming Language :: Python :: 3.12
Provides-Extra: asgi
Requires-Dist: pydantic (>=2,<3)
Requires-Dist: starlette (<1) ; extra == "asgi"
